pyhyperscan/__init__.py
pyhyperscan/hs.dll
pyhyperscan/pyhyperscan.cp38-win_amd64.pyd
pyhyperscan-0.1.9.dist-info/METADATA
pyhyperscan-0.1.9.dist-info/WHEEL
pyhyperscan-0.1.9.dist-info/top_level.txt
pyhyperscan-0.1.9.dist-info/RECORD
