Metadata-Version: 2.1
Name: pyhyperscan
Version: 0.1.9
Summary: A Python wrapper for Hyperscan
Home-page: https://gitee.com/fgc1/regex_engine_py.git
Author: fgc
Author-email: 13654918696@163.com
License: UNKNOWN
Platform: UNKNOWN
Classifier: Programming Language :: Python :: 3
Classifier: Programming Language :: Python :: 3.7
Classifier: Programming Language :: Python :: 3.8
Classifier: Programming Language :: Python :: 3.9
Classifier: Operating System :: Microsoft :: Windows
Classifier: Operating System :: POSIX :: Linux
Requires-Python: >=3.7
Requires-Dist: Cython (>=0.29.0)
